utilsbi_mssql_access/__init__.py
utilsbi_mssql_access/persistence.py
tribanco_utils_bi-1.0.2.dist-info/LICENSE
tribanco_utils_bi-1.0.2.dist-info/METADATA
tribanco_utils_bi-1.0.2.dist-info/WHEEL
tribanco_utils_bi-1.0.2.dist-info/top_level.txt
tribanco_utils_bi-1.0.2.dist-info/RECORD
